investify_utils-2.0.0a10.dist-info/METADATA
investify_utils-2.0.0a10.dist-info/WHEEL
investify_utils-2.0.0a10.dist-info/entry_points.txt
investify_utils/__init__.py
investify_utils/helpers.py
investify_utils/kafka/__init__.py
investify_utils/kafka/sync_consumer.py
investify_utils/kafka/sync_producer.py
investify_utils/logging.py
investify_utils/postgres/__init__.py
investify_utils/postgres/async_client.py
investify_utils/postgres/sync_client.py
investify_utils/s3/__init__.py
investify_utils/s3/sync_client.py
investify_utils-2.0.0a10.dist-info/RECORD
