Metadata-Version: 2.1
Name: investify-utils
Version: 2.0.0a10
Summary: Shared utilities for Investify services
Author-Email: Investify <dev@investify.vn>
License: MIT
Classifier: Development Status :: 3 - Alpha
Classifier: Intended Audience :: Developers
Classifier: License :: OSI Approved :: MIT License
Classifier: Programming Language :: Python :: 3.12
Classifier: Topic :: Software Development :: Libraries :: Python Modules
Project-URL: Repository, https://gitlab.com/investify-vn/core/investify-utils
Requires-Python: >=3.12
Provides-Extra: postgres
Requires-Dist: pandas>=2.0; extra == "postgres"
Requires-Dist: pangres>=4.0; extra == "postgres"
Requires-Dist: sqlalchemy>=2.0; extra == "postgres"
Requires-Dist: psycopg[binary]>=3.0; extra == "postgres"
Provides-Extra: postgres-async
Requires-Dist: pandas>=2.0; extra == "postgres-async"
Requires-Dist: sqlalchemy>=2.0; extra == "postgres-async"
Requires-Dist: asyncpg>=0.29; extra == "postgres-async"
Provides-Extra: kafka
Requires-Dist: confluent-kafka[avro,schemaregistry]>=2.0; extra == "kafka"
Provides-Extra: s3
Requires-Dist: boto3>=1.34; extra == "s3"
Provides-Extra: helpers
Requires-Dist: pandas>=2.0; extra == "helpers"
Requires-Dist: numpy>=2.0; extra == "helpers"
Provides-Extra: dev
Requires-Dist: pytest; extra == "dev"
Requires-Dist: pytest-asyncio; extra == "dev"
Requires-Dist: ruff; extra == "dev"
